{"the ville": {"moonlight tavern": {"bathroom": ["bathroom sink", "toilet"], "sing": ["game console"], "kitchen": ["cooking area", "kitchen sink", "refrigerator"], "front desk": ["refrigerator"], "bar customer seating": ["bar seat"]}, "supermarket": {"home appliance area": ["shelf"], "food area": ["grocery store shelf", "computer desk", "shelf"], "checkout counter": ["computer desk", "behind the counter"], "outdoor gear section": ["shelf"]}, "johnson park": {"lake": ["log bridge"], "basketball court": []}, "frank's apartment": {"frank's room": ["bed", "desk", "refrigerator", "closet", "kitchen sink", "cooking area", "seat"], "frank's bathroom": ["bathroom sink", "shower", "toilet"]}, "hobbs cafe": {"meeting area": ["shelf", "piano", "desk"], "cafe": ["cafe customer seating"], "front desk": ["blackboard", "behind the cafe counter"]}, "restaurant": {"dining area": ["seat", "table"]}, "library": {"room": ["bookshelf", "computer desk", "computer", "library sofa"]}, "gym": {"room": ["treadmill"]}, "classroom": {"classroom": ["seat"]}, "cichengege's apartment": {}, "carlos gomez's apartment": {}, "artist's co-living space": {"abigail chen's bathroom": [], "kitchen": ["kitchen sink", "cooking area", "toaster"], "common room": ["seat", "common room sofa"]}}}