{
  "persona": {
    "christopher gardner": {
      "movement": [
        119,
        77
      ],
      "pronunciatio": "\ud83c\udf73\ud83d\ude0a",
      "description": "attending school (eating breakfast) @ the ville:gardner family's house:kitchen:<random>",
      "chat": null
    },
    "linda": {
      "movement": [
        123,
        77
      ],
      "pronunciatio": "\ud83d\udcdd\ud83e\udd14",
      "description": "having breakfast and reviewing plans for the day (jotting down key points for the family gathering discussion) @ the ville:gardner family's house:kitchen:<random>",
      "chat": null
    },
    "tom moreno": {
      "movement": [
        97,
        74
      ],
      "pronunciatio": "\ud83d\ude34\ud83d\ude10",
      "description": "sleeping @ the ville:moreno family's house:tom moreno's bedroom:bed",
      "chat": null
    },
    "chris gardner": {
      "movement": [
        34,
        86
      ],
      "pronunciatio": "\ud83d\ude34\ud83d\ude10",
      "description": "sleeping @ the ville:gardner family's house:chris gardner's room:bed",
      "chat": null
    },
    "carmen ortiz": {
      "movement": [
        63,
        74
      ],
      "pronunciatio": "\ud83d\ude34\ud83d\ude10",
      "description": "sleeping @ the ville:tamara taylor and carmen ortiz's house:carmen ortiz's room:bed",
      "chat": null
    },
    "jane moreno": {
      "movement": [
        98,
        70
      ],
      "pronunciatio": "\ud83d\udca1\ud83e\udd14",
      "description": "working on NFT music projects and researching decentralization in the art field (brainstorming new ideas for combining NFT music with visual arts) @ the ville:moreno family's house:common room:desk",
      "chat": null
    },
    "tamara taylor": {
      "movement": [
        59,
        74
      ],
      "pronunciatio": "\ud83d\udcdd\ud83e\udd14",
      "description": "working on refining the FitCoin launch plan (drafting a timeline for the FitCoin test issuance)   @ the ville:tamara taylor and carmen ortiz's house:tamara taylor's room:desk",
      "chat": null
    },
    "latoya williams": {
      "movement": [
        19,
        14
      ],
      "pronunciatio": "\ud83d\udcf7\ud83d\ude0a",
      "description": "having breakfast and reviewing her photography plans for the day (organizing her photography equipment for the day) @ the ville:artist's co-living space:latoya williams's room:closet",
      "chat": null
    },
    "rajiv patel": {
      "movement": [
        27,
        12
      ],
      "pronunciatio": "\ud83d\ude34\ud83d\ude10",
      "description": "sleeping @ the ville:artist's co-living space:rajiv patel's room:bed",
      "chat": null
    },
    "francisco lopez": {
      "movement": [
        17,
        26
      ],
      "pronunciatio": "\ud83d\ude34\ud83d\ude10",
      "description": "sleeping @ the ville:artist's co-living space:francisco lopez's room:bed",
      "chat": null
    },
    "cichengege": {
      "movement": [
        25,
        70
      ],
      "pronunciatio": "\ud83d\ude34\ud83d\ude0c",
      "description": "sleeping @ the ville:cichengege's apartment:cichengege's room:bed",
      "chat": null
    },
    "frank": {
      "movement": [
        33,
        68
      ],
      "pronunciatio": "\ud83d\ude34\ud83d\ude10",
      "description": "sleeping @ the ville:frank's apartment:frank's room:bed",
      "chat": null
    },
    "arthur burton": {
      "movement": [
        9,
        70
      ],
      "pronunciatio": "\ud83d\ude34\ud83d\ude10",
      "description": "sleeping @ the ville:arthur burton's apartment:arthur burton's room:bed",
      "chat": null
    },
    "carlos gomez": {
      "movement": [
        41,
        67
      ],
      "pronunciatio": "\ud83d\ude34\ud83d\ude10",
      "description": "sleeping @ the ville:carlos gomez's apartment:carlos gomez's room:bed",
      "chat": null
    },
    "mk": {
      "movement": [
        82,
        69
      ],
      "pronunciatio": "\ud83d\udcca\ud83e\udd14",
      "description": "continuing his research on the AI economic system, diving deeper into coding and testing to refine the decentralized financial system model (analyzing the performance of the decentralized financial system model) @ the ville:mk's house:classroom:desk",
      "chat": null
    },
    "kiki": {
      "movement": [
        16,
        70
      ],
      "pronunciatio": "\ud83d\ude34\ud83d\ude10",
      "description": "sleeping @ the ville:kiki's apartment:kiki's room:bed",
      "chat": null
    }
  },
  "meta": {
    "curr_time": "March 14, 2025, 08:41:10"
  }
}